{"nodes": [{"id": "d_projects_medi_help_backend_app_schemas_medication_py", "label": "medication.py", "file_type": "code", "source_file": "backend/app/schemas/medication.py", "source_location": "L1"}, {"id": "schemas_medication_medicationschedulecreate", "label": "MedicationScheduleCreate", "file_type": "code", "source_file": "backend/app/schemas/medication.py", "source_location": "L12"}, {"id": "basemodel", "label": "BaseModel", "file_type": "code", "source_file": "", "source_location": ""}, {"id": "schemas_medication_medicationscheduleresponse", "label": "MedicationScheduleResponse", "file_type": "code", "source_file": "backend/app/schemas/medication.py", "source_location": "L21"}, {"id": "schemas_medication_medicationcreate", "label": "MedicationCreate", "file_type": "code", "source_file": "backend/app/schemas/medication.py", "source_location": "L30"}, {"id": "schemas_medication_medicationupdate", "label": "MedicationUpdate", "file_type": "code", "source_file": "backend/app/schemas/medication.py", "source_location": "L40"}, {"id": "schemas_medication_medicationresponse", "label": "MedicationResponse", "file_type": "code", "source_file": "backend/app/schemas/medication.py", "source_location": "L51"}, {"id": "schemas_medication_confirmextractedmedicationsrequest", "label": "ConfirmExtractedMedicationsRequest", "file_type": "code", "source_file": "backend/app/schemas/medication.py", "source_location": "L73"}], "edges": [{"source": "d_projects_medi_help_backend_app_schemas_medication_py", "target": "datetime", "relation": "imports_from", "context": "import", "confidence": "EXTRACTED", "source_file": "backend/app/schemas/medication.py", "source_location": "L1", "weight": 1.0}, {"source": "d_projects_medi_help_backend_app_schemas_medication_py", "target": "typing", "relation": "imports_from", "context": "import", "confidence": "EXTRACTED", "source_file": "backend/app/schemas/medication.py", "source_location": "L2", "weight": 1.0}, {"source": "d_projects_medi_help_backend_app_schemas_medication_py", "target": "uuid", "relation": "imports_from", "context": "import", "confidence": "EXTRACTED", "source_file": "backend/app/schemas/medication.py", "source_location": "L3", "weight": 1.0}, {"source": "d_projects_medi_help_backend_app_schemas_medication_py", "target": "pydantic", "relation": "imports_from", "context": "import", "confidence": "EXTRACTED", "source_file": "backend/app/schemas/medication.py", "source_location": "L5", "weight": 1.0}, {"source": "d_projects_medi_help_backend_app_schemas_medication_py", "target": "schemas_medication_medicationschedulecreate", "relation": "contains", "confidence": "EXTRACTED", "source_file": "backend/app/schemas/medication.py", "source_location": "L12", "weight": 1.0}, {"source": "schemas_medication_medicationschedulecreate", "target": "basemodel", "relation": "inherits", "confidence": "EXTRACTED", "source_file": "backend/app/schemas/medication.py", "source_location": "L12", "weight": 1.0}, {"source": "d_projects_medi_help_backend_app_schemas_medication_py", "target": "schemas_medication_medicationscheduleresponse", "relation": "contains", "confidence": "EXTRACTED", "source_file": "backend/app/schemas/medication.py", "source_location": "L21", "weight": 1.0}, {"source": "schemas_medication_medicationscheduleresponse", "target": "schemas_medication_medicationschedulecreate", "relation": "inherits", "confidence": "EXTRACTED", "source_file": "backend/app/schemas/medication.py", "source_location": "L21", "weight": 1.0}, {"source": "d_projects_medi_help_backend_app_schemas_medication_py", "target": "schemas_medication_medicationcreate", "relation": "contains", "confidence": "EXTRACTED", "source_file": "backend/app/schemas/medication.py", "source_location": "L30", "weight": 1.0}, {"source": "schemas_medication_medicationcreate", "target": "basemodel", "relation": "inherits", "confidence": "EXTRACTED", "source_file": "backend/app/schemas/medication.py", "source_location": "L30", "weight": 1.0}, {"source": "d_projects_medi_help_backend_app_schemas_medication_py", "target": "schemas_medication_medicationupdate", "relation": "contains", "confidence": "EXTRACTED", "source_file": "backend/app/schemas/medication.py", "source_location": "L40", "weight": 1.0}, {"source": "schemas_medication_medicationupdate", "target": "basemodel", "relation": "inherits", "confidence": "EXTRACTED", "source_file": "backend/app/schemas/medication.py", "source_location": "L40", "weight": 1.0}, {"source": "d_projects_medi_help_backend_app_schemas_medication_py", "target": "schemas_medication_medicationresponse", "relation": "contains", "confidence": "EXTRACTED", "source_file": "backend/app/schemas/medication.py", "source_location": "L51", "weight": 1.0}, {"source": "schemas_medication_medicationresponse", "target": "basemodel", "relation": "inherits", "confidence": "EXTRACTED", "source_file": "backend/app/schemas/medication.py", "source_location": "L51", "weight": 1.0}, {"source": "d_projects_medi_help_backend_app_schemas_medication_py", "target": "schemas_medication_confirmextractedmedicationsrequest", "relation": "contains", "confidence": "EXTRACTED", "source_file": "backend/app/schemas/medication.py", "source_location": "L73", "weight": 1.0}, {"source": "schemas_medication_confirmextractedmedicationsrequest", "target": "basemodel", "relation": "inherits", "confidence": "EXTRACTED", "source_file": "backend/app/schemas/medication.py", "source_location": "L73", "weight": 1.0}], "raw_calls": []}